csc_cyb600_time/__init__.py
csc_cyb600_time/main.py
csc_cyb600_time_phakousd-1.0.6.data/scripts/say-time-cyb600
csc_cyb600_time_phakousd-1.0.6.dist-info/METADATA
csc_cyb600_time_phakousd-1.0.6.dist-info/WHEEL
csc_cyb600_time_phakousd-1.0.6.dist-info/top_level.txt
csc_cyb600_time_phakousd-1.0.6.dist-info/RECORD
