Metadata-Version: 2.1
Name: csc-cyb600-time-phakousd
Version: 1.0.6
Author: Dara Phakousonh
Author-email: phakoud@canisius.edu
License: Apache License Version 2.0
Requires-Dist: Flask
